tacview_timesync/__init__.py
tacview_timesync/tvts.py
tacview_timesync-0.1.0.dist-info/METADATA
tacview_timesync-0.1.0.dist-info/WHEEL
tacview_timesync-0.1.0.dist-info/entry_points.txt
tacview_timesync-0.1.0.dist-info/RECORD
