Metadata-Version: 2.1
Name: tacview-timesync
Version: 0.1.0
Summary: Calculate new video start timestamp from track event time and video event delta
Author: Brian Peterson
Author-email: brian@epetersons.com
Requires-Python: >=3.10,<4.0
Classifier: Programming Language :: Python :: 3
Classifier: Programming Language :: Python :: 3.10
Classifier: Programming Language :: Python :: 3.11
Requires-Dist: xattr (>=0.10.1,<0.11.0)
